evmspec/__init__.py
evmspec/_new.cpython-311-i386-linux-musl.so
evmspec/_new.py
evmspec/_new__mypyc.cpython-311-i386-linux-musl.so
evmspec/py.typed
evmspec/data/__init__.py
evmspec/data/_cache.py
evmspec/data/_enum.py
evmspec/data/_ids.py
evmspec/data/_main.py
evmspec/data/uints.py
evmspec/structs/__init__.py
evmspec/structs/block.py
evmspec/structs/header.py
evmspec/structs/log.py
evmspec/structs/receipt.py
evmspec/structs/transaction.py
evmspec/structs/trace/__init__.py
evmspec/structs/trace/_base.py
evmspec/structs/trace/call.py
evmspec/structs/trace/create.py
evmspec/structs/trace/reward.py
evmspec/structs/trace/suicide.py
evmspec-0.4.7.dist-info/METADATA
evmspec-0.4.7.dist-info/WHEEL
evmspec-0.4.7.dist-info/top_level.txt
evmspec-0.4.7.dist-info/RECORD
evmspec-0.4.7.dist-info/licenses/LICENSE
